AUTHORS.rst
CONTRIBUTING.rst
HISTORY.rst
LICENSE
MANIFEST.in
README.rst
setup.cfg
setup.py
appointments/__init__.py
appointments/appointments.py
appointments.egg-info/PKG-INFO
appointments.egg-info/SOURCES.txt
appointments.egg-info/dependency_links.txt
appointments.egg-info/not-zip-safe
appointments.egg-info/top_level.txt
test/test_appointments.py