Metadata-Version: 1.1
Name: appointments
Version: 0.1.0
Summary: Appointments manager base on iCalendar`s RFC RRULEs
Home-page: https://github.com/diegoponciano/appointments
Author: Diego Ponciano
Author-email: dgo.ponciano@gmail.com
License: MIT
Keywords: appointments
Platform: UNKNOWN
Classifier: Development Status :: 2 - Pre-Alpha
Classifier: Intended Audience :: Developers
Classifier: License :: OSI Approved :: MIT License
Classifier: Natural Language :: English
Classifier: Programming Language :: Python :: 2
Classifier: Programming Language :: Python :: 2.6
Classifier: Programming Language :: Python :: 2.7
Classifier: Programming Language :: Python :: 3
Classifier: Programming Language :: Python :: 3.3
Classifier: Programming Language :: Python :: Implementation :: PyPy
